{
  "results": [
    {
      "id": 1,
      "name": "Green House",
      "collaborator": [
        { "id": 1, "name": "adit" },
        { "id": 2, "name": "Luhung" },
        { "id": 3, "name": "miftha" }
      ]
    },
    {
      "id": 2,
      "name": "Cyber Punk",
      "collaborator": [
        { "id": 1, "name": "adit" },
        { "id": 2, "name": "Luhung" },
        { "id": 3, "name": "miftha" }
      ]
    },
    {
      "id": 3,
      "name": "Easy Cripto",
      "collaborator": [
        { "id": 1, "name": "adit" },
        { "id": 2, "name": "Luhung" },
        { "id": 3, "name": "miftha" }
      ]
    },
    {
      "id": 4,
      "name": "Travel App",
      "collaborator": [
        { "id": 1, "name": "adit" },
        { "id": 2, "name": "Luhung" },
        { "id": 3, "name": "miftha" }
      ]
    },
    {
      "id": 5,
      "name": "Landing Page",
      "collaborator": [
        { "id": 1, "name": "adit" },
        { "id": 2, "name": "Luhung" },
        { "id": 3, "name": "miftha" }
      ]
    },
    {
      "id": 6,
      "name": "Government App",
      "collaborator": [
        { "id": 1, "name": "adit" },
        { "id": 2, "name": "Luhung" },
        { "id": 3, "name": "miftha" }
      ]
    },
    {
      "id": 7,
      "name": "Company Profile",
      "collaborator": [
        { "id": 1, "name": "adit" },
        { "id": 2, "name": "Luhung" },
        { "id": 3, "name": "miftha" }
      ]
    },
    {
      "id": 8,
      "name": "Easy NFT",
      "collaborator": [
        { "id": 1, "name": "adit" },
        { "id": 2, "name": "Luhung" },
        { "id": 3, "name": "miftha" }
      ]
    },
    {
      "id": 9,
      "name": "Go To",
      "collaborator": [
        { "id": 1, "name": "adit" },
        { "id": 2, "name": "Luhung" },
        { "id": 3, "name": "miftha" }
      ]
    },
    {
      "id": 10,
      "name": "Company Profile Wings",
      "collaborator": [
        { "id": 1, "name": "adit" },
        { "id": 2, "name": "Luhung" },
        { "id": 3, "name": "miftha" }
      ]
    }
  ],
  "total": 10
}
